PyAutoMakerFace/__init__.py
PyAutoMakerFace/__main__.py
PyAutoMakerFace/models/deploy.prototxt
PyAutoMakerFace/models/mask_classifier.tflite
PyAutoMakerFace/models/openface_nn4.small2.v1.t7
PyAutoMakerFace/models/res10_300x300_ssd_iter_140000.caffemodel
PyAutoMakerFace-0.1.4.dist-info/LICENSE
PyAutoMakerFace-0.1.4.dist-info/METADATA
PyAutoMakerFace-0.1.4.dist-info/WHEEL
PyAutoMakerFace-0.1.4.dist-info/top_level.txt
PyAutoMakerFace-0.1.4.dist-info/RECORD
